dc09_spt/__init__.py
dc09_spt/dc09_spt.py
dc09_spt/param.py
dc09_spt/comm/__init__.py
dc09_spt/comm/transpath.py
dc09_spt/comm/transpathtcp.py
dc09_spt/comm/transpathudp.py
dc09_spt/msg/__init__.py
dc09_spt/msg/dc03_msg.py
dc09_spt/msg/dc05_msg.py
dc09_spt/msg/dc09_msg.py
dc09_spt-0.0.4.dist-info/LICENSE
dc09_spt-0.0.4.dist-info/METADATA
dc09_spt-0.0.4.dist-info/WHEEL
dc09_spt-0.0.4.dist-info/top_level.txt
dc09_spt-0.0.4.dist-info/RECORD
