Metadata-Version: 2.1
Name: dc09-spt
Version: 0.0.4
Summary: A dialler implementation using the SIA-DC09 protocol
Home-page: https://github.com/jvanovost/dc09_spt
Author: Jacq. van Ovost
Author-email: jacq.van.ovost@gmail.com
License: UNKNOWN
Keywords: DC09,SIA DC09,SPT,Alarm transmitter
Platform: UNKNOWN
Classifier: Programming Language :: Python :: 3
Classifier: License :: OSI Approved :: Apache Software License
Classifier: Operating System :: OS Independent
Requires-Python: >=3.6
